{
    "tags": [],
    "description": "",
    "objects": [
        {
            "id": 1094009748,
            "classId": 11266125,
            "description": "",
            "geometryType": "polygon",
            "labelerLogin": "n.litvinenko",
            "createdAt": "2022-11-10T13:22:05.380Z",
            "updatedAt": "2023-05-29T10:52:16.055Z",
            "tags": [],
            "classTitle": "Nail",
            "points": {
                "exterior": [
                    [
                        999.0,
                        374.0
                    ],
                    [
                        985.0,
                        400.0
                    ],
                    [
                        977.0,
                        417.0
                    ],
                    [
                        975.0,
                        425.0
                    ],
                    [
                        969.0,
                        444.0
                    ],
                    [
                        964.0,
                        450.0
                    ],
                    [
                        955.0,
                        461.0
                    ],
                    [
                        943.0,
                        467.0
                    ],
                    [
                        940.0,
                        473.0
                    ],
                    [
                        946.0,
                        490.0
                    ],
                    [
                        950.0,
                        501.0
                    ],
                    [
                        960.0,
                        511.0
                    ],
                    [
                        965.0,
                        522.0
                    ],
                    [
                        962.0,
                        533.0
                    ],
                    [
                        954.0,
                        546.0
                    ],
                    [
                        948.0,
                        559.0
                    ],
                    [
                        949.0,
                        568.0
                    ],
                    [
                        942.0,
                        581.0
                    ],
                    [
                        944.0,
                        592.0
                    ],
                    [
                        948.0,
                        610.0
                    ],
                    [
                        943.0,
                        631.0
                    ],
                    [
                        929.0,
                        643.0
                    ],
                    [
                        919.0,
                        650.0
                    ],
                    [
                        917.0,
                        671.0
                    ],
                    [
                        924.0,
                        685.0
                    ],
                    [
                        930.0,
                        696.0
                    ],
                    [
                        930.0,
                        704.0
                    ],
                    [
                        929.0,
                        710.0
                    ],
                    [
                        927.0,
                        727.0
                    ],
                    [
                        920.0,
                        735.0
                    ],
                    [
                        909.0,
                        748.0
                    ],
                    [
                        906.0,
                        768.0
                    ],
                    [
                        909.0,
                        778.0
                    ],
                    [
                        920.0,
                        798.0
                    ],
                    [
                        923.0,
                        804.0
                    ],
                    [
                        927.0,
                        823.0
                    ],
                    [
                        929.0,
                        834.0
                    ],
                    [
                        926.0,
                        849.0
                    ],
                    [
                        923.0,
                        868.0
                    ],
                    [
                        917.0,
                        884.0
                    ],
                    [
                        917.0,
                        897.0
                    ],
                    [
                        903.0,
                        912.0
                    ],
                    [
                        900.0,
                        933.0
                    ],
                    [
                        902.0,
                        954.0
                    ],
                    [
                        904.0,
                        963.0
                    ],
                    [
                        915.0,
                        983.0
                    ],
                    [
                        918.0,
                        990.0
                    ],
                    [
                        921.0,
                        999.0
                    ],
                    [
                        999.0,
                        999.0
                    ]
                ],
                "interior": []
            }
        },
        {
            "id": 1094009749,
            "classId": 11266126,
            "description": "",
            "geometryType": "bitmap",
            "labelerLogin": "n.litvinenko",
            "createdAt": "2022-11-10T13:22:05.380Z",
            "updatedAt": "2023-05-29T10:52:16.055Z",
            "tags": [],
            "classTitle": "Primary Capillary",
            "bitmap": {
                "origin": [
                    875,
                    327
                ],
                "data": "eJzrDPBz5+WS4mJgYOD19HAJAtIpQCzLyAwk0xij5YAUW4BPiCuQ/v///9Kb8+8CWYwlQX7BDA7PbqQBOe2eLo4hFXNCJ+zmPWzA46K5IkC8d4GojcODNVMPdZjOcrvIoRXKsk9gk7L8TdsP735MdN2xry1gppLPZ9Y86wNV4c6Kxj8PPXnVvNH9Wtniu0skq2Y3+nP+WB3cx/ii+GtgeIHFy0lVDs7LA1+55682Nlv5W+2+yj3tHc2eSztPTJ+b6TPT7bN1baripNi60+W2EVWP7PSBTmLwdPVzWeeU0AQA4qFWbA=="
            }
        },
        {
            "id": 1094009750,
            "classId": 11266126,
            "description": "",
            "geometryType": "bitmap",
            "labelerLogin": "n.litvinenko",
            "createdAt": "2022-11-10T13:22:05.380Z",
            "updatedAt": "2023-05-29T10:52:16.055Z",
            "tags": [],
            "classTitle": "Primary Capillary",
            "bitmap": {
                "origin": [
                    825,
                    234
                ],
                "data": "eJwB5wEY/olQTkcNChoKAAAADUlIRFIAAACaAAAAlgEDAAAAHPMDLwAAAAZQTFRFAAAA////pdmf3QAAAAF0Uk5TAEDm2GYAAAGPSURBVHic7ZYxTsYwDIUdRSIbuQAi12CiV+EIjAyIhpv1KD1C2TpUNY6dtokTFuY+6ddffWr9nJdIMYDoBZQCArwqZhFX8Ap6xB1crOGAiLOZakgMFzOX6MEluMGbqoip6HvdD6tuNMP4pL2TfQVHgdujamgFg3vVPcEpFbE1XCGtv1oSGTOEpTTaQOBHCdPX5BSfyz6nDMtETczQlU6QoaXiQ6zhBDiNOJfQEgycq4KOc1XQcK4KcmCThl5BxwlQgTnsCtLfMlxlfX7kM6DhgJKvwFwplL3Km37xZa8MR9o+PgMnlLV/1/BHzkTq9YKiVT6q4ZYWcECXIeYYciBZkTdBZKRi4FjPpPjwRcv2JwzciSF7W2XKKe0dOODsGhhw9w305doPWb334tSDozo6LFds3CnTgxDar2/dunXr1q3/yy89eM0OhUJzK/5ZAD57MPRgmsqqwTApjbR21q9+0a+5B9PwNmqYpjo9QNPNLIWVP40Qi4Y0GEIbwbC19lR16kDXue6PSVbJ96A93H8B0Hw/HXk2T3EAAAAASUVORK5CYIIkadtN"
            }
        },
        {
            "id": 1094009751,
            "classId": 11266126,
            "description": "",
            "geometryType": "bitmap",
            "labelerLogin": "n.litvinenko",
            "createdAt": "2022-11-10T13:22:05.380Z",
            "updatedAt": "2023-05-29T10:52:16.055Z",
            "tags": [],
            "classTitle": "Primary Capillary",
            "bitmap": {
                "origin": [
                    866,
                    416
                ],
                "data": "eJzrDPBz5+WS4mJgYOD19HAJAtJuQCzGyAwk3fMqDIAUW4BPiCuQ/v///9Kb8+8CWYwlQX7BDA7PbqQBOSmeLo4hFXNc+zbyHlDgYekN2pHS6NFzKEpT6WCGR2SLoIbmmhquiuO9/t9u/zdq+Wqlqiw7w8VV+Vh81Crvvx4PltQJ7+Jff9Vv4p5rK7225DaFiTEFlOw6ctK8sdPnne/PhdsPBU/5yMi9TXnxuQlfVYD2MXi6+rmsc0poAgCLI0UF"
            }
        },
        {
            "id": 1094009752,
            "classId": 11266126,
            "description": "",
            "geometryType": "bitmap",
            "labelerLogin": "n.litvinenko",
            "createdAt": "2022-11-10T13:22:05.380Z",
            "updatedAt": "2023-05-29T10:52:16.055Z",
            "tags": [],
            "classTitle": "Primary Capillary",
            "bitmap": {
                "origin": [
                    840,
                    474
                ],
                "data": "eJzrDPBz5+WS4mJgYOD19HAJAtJGQMzHyAwkwz3vqgAptgCfEFcg/f///6U3598FshhLgvyCGRye3UgDcpw9XRxDKubontrIy6DI43yxX0PjJoObrdvpCBGPtieTnkWWNRysD9Zec6rBz89rv2vI3Qk6Of++1Cw2vLvNtmritx+tSoWMutLSbjNmB4YDjWPwdPVzWeeU0AQAcuAz8g=="
            }
        },
        {
            "id": 1094009753,
            "classId": 11266126,
            "description": "",
            "geometryType": "bitmap",
            "labelerLogin": "n.litvinenko",
            "createdAt": "2022-11-10T13:22:05.380Z",
            "updatedAt": "2023-05-29T10:52:16.055Z",
            "tags": [],
            "classTitle": "Primary Capillary",
            "bitmap": {
                "origin": [
                    865,
                    513
                ],
                "data": "eJzrDPBz5+WS4mJgYOD19HAJAtJqQMzPyAwkNwXoCwMptgCfEFcg/f///6U3598FshhLgvyCGRye3UgDcnw8XRxDKubI9mzkbTAQYOavdTzJliL8bFEHy+LUKT0fUrs4Ps8/lH5yE29Bm8arDZ5yJZ97cj60+l5ZMCmxNX2jiZtJ9aTbk65Hyf48vO47u+EliaA/yyqtgOYyeLr6uaxzSmgCAI6AOlQ="
            }
        },
        {
            "id": 1094009754,
            "classId": 11266126,
            "description": "",
            "geometryType": "bitmap",
            "labelerLogin": "n.litvinenko",
            "createdAt": "2022-11-10T13:22:05.380Z",
            "updatedAt": "2023-05-29T10:52:16.055Z",
            "tags": [],
            "classTitle": "Primary Capillary",
            "bitmap": {
                "origin": [
                    824,
                    589
                ],
                "data": "eJzrDPBz5+WS4mJgYOD19HAJAtJhQKzAyAwkNz2WzQBSbAE+Ia5A+v///0tvzr8LZDGWBPkFMzg8u5EG5HR5ujiGVMzxnbBR8IgCD8tTxQAPTq2jSx9eiuny/jGh4WPkj9YaF+vFyf4KFir8eo9+P3Zb2CTPq5FiMXmqkzRbpGH+3/bfa7ql5iq61BcLHwqoSTjNIPPVdM/24203TsuE7WXau6b9zbp+M/OHW+SqQ2JKNy7I3tTb/3rtzl2L1HZrGh+68+Kmde0yQe3ayQ5y7W+iT02IVGUDuorB09XPZZ1TQhMAYcdYEw=="
            }
        },
        {
            "id": 1094009755,
            "classId": 11266126,
            "description": "",
            "geometryType": "bitmap",
            "labelerLogin": "n.litvinenko",
            "createdAt": "2022-11-10T13:22:05.380Z",
            "updatedAt": "2023-05-29T10:52:16.055Z",
            "tags": [],
            "classTitle": "Primary Capillary",
            "bitmap": {
                "origin": [
                    749,
                    814
                ],
                "data": "eJzrDPBz5+WS4mJgYOD19HAJAtJdQCzKyAwkF1c+2Qik2AJ8QlyB9P///5fenH8XyGIsCfILZnB4diMNyFno6eIYUjEndsJG0cMKPC5PlzdNEpQ4uthx+sZHetlLvL09Dz4uYvrcs9arpnAXs2DhAcW9q+ZsZV7cn7vIy+KCNu+ieKXXW1/sPCC/qXTp+k+n+5JuNCV48XcysGokLbsasOhySfiHqIr08oV5G9p9Uud0POaviUyazThrZ674ox0rZfNXfHEQX9Skf2ghtxS39IS8jo/zPHjuevZ/csj79yxI8GenjP5fxk2dOYsLGKdPBzqWwdPVz2WdU0ITAN4YZSw="
            }
        },
        {
            "id": 1094009756,
            "classId": 11266126,
            "description": "",
            "geometryType": "bitmap",
            "labelerLogin": "n.litvinenko",
            "createdAt": "2022-11-10T13:22:05.380Z",
            "updatedAt": "2023-05-29T10:52:16.055Z",
            "tags": [],
            "classTitle": "Primary Capillary",
            "bitmap": {
                "origin": [
                    824,
                    550
                ],
                "data": "eJzrDPBz5+WS4mJgYOD19HAJAtI2QCzMyAwkv534cwlIsQX4hLgC6f///y+9Of8ukMVYEuQXzODw7EYakJPk6eIYUjHHtnej4AEFHuajSxd84eh5dPFERs8hDj3NIo0yphUf/p7cxrKDx9vGwKxAVzv9TKfPPY8v3KmHj37Ibjb4c2mh2r/Juj6yjO+4Z0cciX/D5+/SmxS/+V1fyakT/5rzPkwQZ4+1vn6z5NlVoG0Mnq5+LuucEpoAAkJIjQ=="
            }
        },
        {
            "id": 1094009757,
            "classId": 11266126,
            "description": "",
            "geometryType": "bitmap",
            "labelerLogin": "n.litvinenko",
            "createdAt": "2022-11-10T13:22:05.380Z",
            "updatedAt": "2023-05-29T10:52:16.055Z",
            "tags": [],
            "classTitle": "Primary Capillary",
            "bitmap": {
                "origin": [
                    726,
                    848
                ],
                "data": "eJzrDPBz5+WS4mJgYOD19HAJAtKlQGzHyAwk9UOPBQAptgCfEFcg/f///6U3598FshhLgvyCGRye3UgDcrZ7ujiGVMxpnbRR8LABh+vS4oeTBE263ILdis0+cmjGPvmjvLvpeOyad541Pxq6ar0typq+Mr1vFK9d1GAjJ/HxTPqDtl/O0T7s+y/VV08QP8H95OdcmbdLy34L7rQ9s1+Nmd/GTKSBsblRVPbKFgeLNy/ZFR6LhNhfW/Z6R8Ps2AM79Pn0K7i7o0VPhzxM+uXVJctYuM2U/UgP27p5uVntj7M31u2sPXeVaX6C7EPjkhKTv+2hOk33ryz4MNP3KfvUyb0PipcbZwO9wODp6ueyzimhCQDTu26p"
            }
        },
        {
            "id": 1094009758,
            "classId": 11266126,
            "description": "",
            "geometryType": "bitmap",
            "labelerLogin": "n.litvinenko",
            "createdAt": "2022-11-10T13:22:05.380Z",
            "updatedAt": "2023-05-29T10:52:16.055Z",
            "tags": [],
            "classTitle": "Primary Capillary",
            "bitmap": {
                "origin": [
                    794,
                    754
                ],
                "data": "eJzrDPBz5+WS4mJgYOD19HAJAtKqQMzDyAwk739+tg9IsQX4hLgC6f///y+9Of8ukMVYEuQXzODw7EYakGPi6eIYUjEnOeHH/QMMLEBF/xtc/iUkJLBN/N8QZN/AxJvwSV65g6Xzs3MI01UbhlUP/tczMORtVfdgMGnbAdTP4Onq57LOKaEJALa0L6c="
            }
        },
        {
            "id": 1094009759,
            "classId": 11266126,
            "description": "",
            "geometryType": "bitmap",
            "labelerLogin": "n.litvinenko",
            "createdAt": "2022-11-10T13:22:05.380Z",
            "updatedAt": "2023-05-29T10:52:16.055Z",
            "tags": [],
            "classTitle": "Primary Capillary",
            "bitmap": {
                "origin": [
                    813,
                    713
                ],
                "data": "eJzrDPBz5+WS4mJgYOD19HAJAtJKQCzCyAwkL62qNQRSbAE+Ia5A+v///0tvzr8LZDGWBPkFMzg8u5EG5AR4ujiGVMxRPbNRtMGBg/nCDx2NfBa3nRf7eGNOBsocnNRULmhwdP0khoKQstP3d8/Jt4x6eUnQoWRq31Shy5fceb3kLWcrrnwjtOfU1XKv1du/qdjFsyl927FY9wbQbAZPVz+XdU4JTQDQQDuR"
            }
        },
        {
            "id": 1094009760,
            "classId": 11266126,
            "description": "",
            "geometryType": "bitmap",
            "labelerLogin": "n.litvinenko",
            "createdAt": "2022-11-10T13:22:05.380Z",
            "updatedAt": "2023-05-29T10:52:16.055Z",
            "tags": [],
            "classTitle": "Primary Capillary",
            "bitmap": {
                "origin": [
                    885,
                    207
                ],
                "data": "eJzrDPBz5+WS4mJgYOD19HAJAtJKQMzHyAwkC57HnAFSbAE+Ia5A+v///0tvzr8LZDGWBPkFMzg8u5EG5Fh5ujiGVMxJrjjAwPT/wJK////z8vCcASpmKP7f4GlpoMmvdlPaQeUzI0smv8rT/zeYjz49OEvyxn9DBoYrpwTDfpvukwOawuDp6ueyzimhCQCM1TK+"
            }
        },
        {
            "id": 1094009761,
            "classId": 11266126,
            "description": "",
            "geometryType": "bitmap",
            "labelerLogin": "n.litvinenko",
            "createdAt": "2022-11-10T13:22:05.380Z",
            "updatedAt": "2023-05-29T10:52:16.055Z",
            "tags": [],
            "classTitle": "Primary Capillary",
            "bitmap": {
                "origin": [
                    906,
                    178
                ],
                "data": "eJzrDPBz5+WS4mJgYOD19HAJAtJRQCzPyAwkYz97zANSbAE+Ia5A+v///0tvzr8LZDGWBPkFMzg8u5EG5HR6ujiGVMwJnXCQ96gCj3OvxZMTHJJLm7cGWUe5v+SQsVzwq/mLZ1Cev1pnrgxHv/yDtxsMM1rXsM3MkX9ZZPXTZaU1R3y7jf/J1ADFbPvnE876ek7Xll3+Zr6PeLtz+z/FwpzpT5OfrNi588qk3xqy6R9azk5SuVcmdmM+w6nrC4+cUwmbmFzf8XDhQjuexfanvAOnu8WVvAI6isHT1c9lnVNCEwD2t1g+"
            }
        },
        {
            "id": 1094015006,
            "classId": 11266127,
            "description": "",
            "geometryType": "bitmap",
            "labelerLogin": "n.litvinenko",
            "createdAt": "2022-11-10T13:22:05.380Z",
            "updatedAt": "2023-05-29T10:52:16.055Z",
            "tags": [],
            "classTitle": "Secondary Capillary",
            "bitmap": {
                "origin": [
                    201,
                    578
                ],
                "data": "eJzrDPBz5+WS4mJgYOD19HAJAtLmQKzByAwkE6Z+8AZSbAE+Ia5A+v///0tvzr8LZDGWBPkFMzg8u5EG5EzydHEMqZhT27eb94iCgAu7YIwH57sjJWkavUExTIqTBKs3n7YyPel8pt1xAputY1ux5dNt3t/YO6wnlyRP2dl6uPUFU5wid0wDd+lmE/93+hNMJMQX5WkkPWnoWpnI97BlfoHiTLlr8Vu+Jk0596t7mxSLeu6vs51HMmZyZ2Y8PnSx9IXLvq1dOVG2ATnXG3zTri1Ptvht/j9zY0Tmcj71J0DXMXi6+rmsc0poAgAMXlpp"
            }
        },
        {
            "id": 1094015007,
            "classId": 11266127,
            "description": "",
            "geometryType": "bitmap",
            "labelerLogin": "n.litvinenko",
            "createdAt": "2022-11-10T13:22:05.380Z",
            "updatedAt": "2023-05-29T10:52:16.055Z",
            "tags": [],
            "classTitle": "Secondary Capillary",
            "bitmap": {
                "origin": [
                    617,
                    264
                ],
                "data": "eJzrDPBz5+WS4mJgYOD19HAJAtLGQCzHyAwkd8duaQRSbAE+Ia5A+v///0tvzr8LZDGWBPkFMzg8u5EG5OR7ujiGVMxxPb+R94ACD4uDMtf0ngMaN3UMZu1ec5BDM1jB7qAN11lO7tv9KsL2P5c1J3GGZG25eNw35OLdho3S3xUeO3MXT1tU6ck4X/LF9YbsqAul7yxWHdk2aedK74zsyfeV3b7ptM408q13S172ld3yKSvDXK9XDtdnKAOtZvB09XNZ55TQBAD5KElf"
            }
        },
        {
            "id": 1094015008,
            "classId": 11266127,
            "description": "",
            "geometryType": "bitmap",
            "labelerLogin": "n.litvinenko",
            "createdAt": "2022-11-10T13:22:05.380Z",
            "updatedAt": "2023-05-29T10:52:16.055Z",
            "tags": [],
            "classTitle": "Secondary Capillary",
            "bitmap": {
                "origin": [
                    716,
                    262
                ],
                "data": "eJwBJQHa/olQTkcNChoKAAAADUlIRFIAAACHAAAAOAEDAAAA7bV56QAAAAZQTFRFAAAA////pdmf3QAAAAF0Uk5TAEDm2GYAAADNSURBVHicbZOxFcMgEEPhUVAywm0S1koVslkyikdwScFDOacCyS7/M9JJB8HegT4oOYR0IZNJEaGMUwiIJOC7kwgM+qnKMQO7JT2Gu2PkViBDQlBWJR+JOvG5uZN8F47tQuO5Q5Fyo26pHUxMpIvsLYlZELPAYT2u2JvYF7HPo5BdgrE4Gt+3JiW1WSlJHZmkPevM3Pc0Fq8fFrd9lRmHIa7iFafnWGtq6KkTuXI9VvJ/WSt5hmu8lbi2k9eeA4P271cbSvZCot7a4VX/ADwPh0oWkC8qAAAAAElFTkSuQmCCQDd3kQ=="
            }
        },
        {
            "id": 1094015009,
            "classId": 11266127,
            "description": "",
            "geometryType": "bitmap",
            "labelerLogin": "n.litvinenko",
            "createdAt": "2022-11-10T13:22:05.380Z",
            "updatedAt": "2023-05-29T10:52:16.055Z",
            "tags": [],
            "classTitle": "Secondary Capillary",
            "bitmap": {
                "origin": [
                    769,
                    173
                ],
                "data": "eJzrDPBz5+WS4mJgYOD19HAJAtKxQKzAyAwkvZifzQdSbAE+Ia5A+v///0tvzr8LZDGWBPkFMzg8u5EG5EzxdHEMqZhT2r9R0EWRw+VnckIG5zSnzIhb+keFOHjn3D4syapvoTTvkJ63S4jByxBXB8YPN/cmXG27avaOcW8f89qMm1wSU9IPVn8RujbZefLi9MW9h6d/NZzLPFnidpeRyW/Pk1bfLB3981I1Z+nfnB7WG2C8c/JPm4m2C48LdXbpB8rKTHD/KuHSrD9jB4P5ifgH8R3cbxZ8576bk6Ol+M1yOtB9DJ6ufi7rnBKaAK8QWSs="
            }
        },
        {
            "id": 1094015010,
            "classId": 11266127,
            "description": "",
            "geometryType": "bitmap",
            "labelerLogin": "n.litvinenko",
            "createdAt": "2022-11-10T13:22:05.380Z",
            "updatedAt": "2023-05-29T10:52:16.055Z",
            "tags": [],
            "classTitle": "Secondary Capillary",
            "bitmap": {
                "origin": [
                    820,
                    94
                ],
                "data": "eJzrDPBz5+WS4mJgYOD19HAJAtLeQKzOyAwka7epdwAptgCfEFcg/f///6U3598FshhLgvyCGRye3UgDchZ6ujiGVMzJnbCR10WRx7lZQ0OyMVBCt+ebeyKLF1cL/5fHd0Tdv7a8UdnmcScp30Ug3eV3c5DcYd2V0lnezRaPTNZY6xzmefigw93SqXqpfv+jRxMrA2Yw3q/1MpzVvTXd75ryNuvPRR89Qx7sY9m9bl7AsnXBIvlTNs/omr1TT8/y/jPpcp6jQfH3TUWzmT8kifi/yVkg/D4vKWqmxIPAp+xXd0/f9JR5o3EC+5W/0reBjmXwdPVzWeeU0AQApeJhEg=="
            }
        },
        {
            "id": 1094015011,
            "classId": 11266127,
            "description": "",
            "geometryType": "bitmap",
            "labelerLogin": "n.litvinenko",
            "createdAt": "2022-11-10T13:22:05.380Z",
            "updatedAt": "2023-05-29T10:52:16.055Z",
            "tags": [],
            "classTitle": "Secondary Capillary",
            "bitmap": {
                "origin": [
                    535,
                    29
                ],
                "data": "eJzrDPBz5+WS4mJgYOD19HAJAtKpQCzFyAwkpxxjmAGk2AJ8QlyB9P///5fenH8XyGIsCfILZnB4diMNyGnxdHEMqZgTeuGg4BEFDtYAGX4ZTcWlEVGb5kZ2qT55ofg43mPOk9OtlX0NGrEWx5TWrFpTtOmN0M2GyHXOQjZyqjK3Q3hunzd6ahr45OSqJxaGRwTyl038fPd822rXxP35Ml3lJU7GNdJT4jzKNpZsEIoIenUuy2vTPI8u+ZPbn/w//H1TxmaNxX8ZbywLOZGQ4OgLdA+Dp6ufyzqnhCYAY+pWxQ=="
            }
        },
        {
            "id": 1094015012,
            "classId": 11266127,
            "description": "",
            "geometryType": "bitmap",
            "labelerLogin": "n.litvinenko",
            "createdAt": "2022-11-10T13:22:05.380Z",
            "updatedAt": "2023-05-29T10:52:16.055Z",
            "tags": [],
            "classTitle": "Secondary Capillary",
            "bitmap": {
                "origin": [
                    201,
                    300
                ],
                "data": "eJzrDPBz5+WS4mJgYOD19HAJAtKyQCzFyAwkCyOOfgFSbAE+Ia5A+v///0tvzr8LZDGWBPkFMzg8u5EG5IR7ujiGVMyxPbORt8GAx+Wis2ZQWkvPoShNpUNtaw5wTNFTkt/H8fCR6bVakyO6fIZi6Ru6q9hnBltM8EhQ/h9emTSbV/akyI8PR9jOm2zo0DomGlAZXpeVd4B7d7fmzDMtAZeAVjB4uvq5rHNKaAIANAk8tw=="
            }
        },
        {
            "id": 1094015013,
            "classId": 11266127,
            "description": "",
            "geometryType": "bitmap",
            "labelerLogin": "n.litvinenko",
            "createdAt": "2022-11-10T13:22:05.380Z",
            "updatedAt": "2023-05-29T10:52:16.055Z",
            "tags": [],
            "classTitle": "Secondary Capillary",
            "bitmap": {
                "origin": [
                    28,
                    258
                ],
                "data": "eJzrDPBz5+WS4mJgYOD19HAJAtIGQCzEyAwk1Vec/wmk2AJ8QlyB9P///5fenH8XyGIsCfILZnB4diMNyIn0dHEMqZij2nOQ94ACD3Psxwc3BSVaA6241lpFSLYKVjwTvc6i/dEzMMch63RA5eLAy1vd+BxnTYg0qlgmy/fNzOHFvqYnp+ME+1mnP1BX0lCx+7NoNs+U3j0T37D3aFtx+0byHQNawuDp6ueyzimhCQCcxzxJ"
            }
        },
        {
            "id": 1094015014,
            "classId": 11266127,
            "description": "",
            "geometryType": "bitmap",
            "labelerLogin": "n.litvinenko",
            "createdAt": "2022-11-10T13:22:05.380Z",
            "updatedAt": "2023-05-29T10:52:16.055Z",
            "tags": [],
            "classTitle": "Secondary Capillary",
            "bitmap": {
                "origin": [
                    0,
                    490
                ],
                "data": "eJzrDPBz5+WS4mJgYOD19HAJAtJmQCzCyAwk/7yPWQyk2AJ8QlyB9P///5fenH8XyGIsCfILZnB4diMNyIn1dHEMqZiTeu4sZ4MBD+uDcJkFyilT+sLctXd0PGC692bhk5kmR7sbP8jK/WTcUHrmlJTYtsxUlicFR0T6t+6QNuV9N21V6eZ386+qnRD+tMOs6izvhGRJ6Yn1x45eue69I75uvlX99gvXFYAWMXi6+rmsc0poAgBnJkYD"
            }
        },
        {
            "id": 1094015015,
            "classId": 11266127,
            "description": "",
            "geometryType": "bitmap",
            "labelerLogin": "n.litvinenko",
            "createdAt": "2022-11-10T13:22:05.380Z",
            "updatedAt": "2023-05-29T10:52:16.055Z",
            "tags": [],
            "classTitle": "Secondary Capillary",
            "bitmap": {
                "origin": [
                    97,
                    676
                ],
                "data": "eJzrDPBz5+WS4mJgYOD19HAJAtJOQCzKyAwkTwiuegKk2AJ8QlyB9P///5fenH8XyGIsCfILZnB4diMNyMn3dHEMqZhj2neQ94ACD3PwxwcnOWRbLyY0r5sSKNGYLi+6bnKD6hFNvzkdAZyxTubX1Bjm/xVX7DrKcbF0xcXVdr63LA94LLby9Yx/KWaUIbY19NT3CUazJdeJvQnW2shhklRZPGvJKxOPSlfbKwrPP5Uf5r/20z80vMpaDmg1g6ern8s6p4QmAN1jR+4="
            }
        },
        {
            "id": 1094015016,
            "classId": 11266127,
            "description": "",
            "geometryType": "bitmap",
            "labelerLogin": "n.litvinenko",
            "createdAt": "2022-11-10T13:22:05.380Z",
            "updatedAt": "2023-05-29T10:52:16.055Z",
            "tags": [],
            "classTitle": "Secondary Capillary",
            "bitmap": {
                "origin": [
                    187,
                    456
                ],
                "data": "eJzrDPBz5+WS4mJgYOD19HAJAtI2QCzByAwk5/DzCAIptgCfEFcg/f///6U3598FshhLgvyCGRye3UgDcso8XRxDKubY9u/mPaDA49KroWEstLhxiuMmriCxwulGU0Q6uu09Y274/6g55uIy8WSydBxz3YyoZ+w/FrKWPThwOsFFL5SRXbz0TIMzS1RcWvusi1u2L7nLKhQSHnrlUq7/pCbHifki4on2u6UfvNrmd8jhuGzJ2WqOV8zVwYG3ikznrgC6gMHT1c9lnVNCEwBJE0h3"
            }
        },
        {
            "id": 1094015017,
            "classId": 11266127,
            "description": "",
            "geometryType": "bitmap",
            "labelerLogin": "n.litvinenko",
            "createdAt": "2022-11-10T13:22:05.380Z",
            "updatedAt": "2023-05-29T10:52:16.055Z",
            "tags": [],
            "classTitle": "Secondary Capillary",
            "bitmap": {
                "origin": [
                    0,
                    665
                ],
                "data": "eJzrDPBz5+WS4mJgYOD19HAJAtIcQMzHyAwkNWacvwqk2AJ8QlyB9P///5fenH8XyGIsCfILZnB4diMNyJHydHEMqZiT/OP4B3mepwc3zHsoL/Ev8cfBDwwM/fu5llWW7QaZzuDp6ueyzimhCQDPQySf"
            }
        },
        {
            "id": 1094015018,
            "classId": 11266127,
            "description": "",
            "geometryType": "bitmap",
            "labelerLogin": "n.litvinenko",
            "createdAt": "2022-11-10T13:22:05.380Z",
            "updatedAt": "2023-05-29T10:52:16.055Z",
            "tags": [],
            "classTitle": "Secondary Capillary",
            "bitmap": {
                "origin": [
                    0,
                    459
                ],
                "data": "eJzrDPBz5+WS4mJgYOD19HAJAtI8IDYjM5Bc/lyWEUixBfiEuALp////L705/y6QxVgS5BfM4PDsRhqQI+3p4hhSMSf5x/+Gh//ZWR79P6Dwn9GVZcUDBmaG/VvEWIXNXjsBlTF4uvq5rHNKaAIAlTAiRg=="
            }
        },
        {
            "id": 1094015019,
            "classId": 11266127,
            "description": "",
            "geometryType": "bitmap",
            "labelerLogin": "n.litvinenko",
            "createdAt": "2022-11-10T13:22:05.380Z",
            "updatedAt": "2023-05-29T10:52:16.055Z",
            "tags": [],
            "classTitle": "Secondary Capillary",
            "bitmap": {
                "origin": [
                    3,
                    291
                ],
                "data": "eJzrDPBz5+WS4mJgYOD19HAJAtLiQMzPyAwkTROPiQIptgCfEFcg/f///6U3598FshhLgvyCGRye3UgDcqw9XRxDKubIdm/kPaDAc0DH8EtPHdN8R/+3nHcTOgwC2fWn8T5++Gnpz4Xc6QqzXdmzLnVu+uiX/8fXeP4DBtej0p9/8ZnJAY1h8HT1c1nnlNAEAMh/MI8="
            }
        },
        {
            "id": 1094015020,
            "classId": 11266127,
            "description": "",
            "geometryType": "bitmap",
            "labelerLogin": "n.litvinenko",
            "createdAt": "2022-11-10T13:22:05.380Z",
            "updatedAt": "2023-05-29T10:52:16.055Z",
            "tags": [],
            "classTitle": "Secondary Capillary",
            "bitmap": {
                "origin": [
                    342,
                    247
                ],
                "data": "eJwBHwHg/olQTkcNChoKAAAADUlIRFIAAABRAAAARQEDAAAACAaY+AAAAAZQTFRFAAAA////pdmf3QAAAAF0Uk5TAEDm2GYAAADHSURBVHicldLBDcMgDAVQoxw4skHZpGxWMlpGYQSOHKr+UjX5/pVySDk9RcQy3zb7nqUZz9LFT/HLbeoqzvJDlksJKx3FlsVJHC+4nNfM7gR3cU+yTwBjZwD68XkBTpvXRxV5bG1kwEb/BDjc8V93cbvuzztp+KCBJu6+AHm441MWA1K/ru6yeW+5u+MIw21MM8Dghawyz7oWH9AWeSk144Rm+XQkOuNkuuElKznxYNFmd3YKu7FTdHouCe/MMHzAUSyN7pN5AxF4dPN/W07tAAAAAElFTkSuQmCCIo14XQ=="
            }
        },
        {
            "id": 1094015021,
            "classId": 11266127,
            "description": "",
            "geometryType": "bitmap",
            "labelerLogin": "n.litvinenko",
            "createdAt": "2022-11-10T13:22:05.380Z",
            "updatedAt": "2023-05-29T10:52:16.055Z",
            "tags": [],
            "classTitle": "Secondary Capillary",
            "bitmap": {
                "origin": [
                    83,
                    341
                ],
                "data": "eJzrDPBz5+WS4mJgYOD19HAJAtIxQCzLyAwiVWdeAlJsAT4hrkD6////S2/OvwtkMZYE+QUzODy7kQbkdHm6OIZUzCnt3yh4RIGH5aOAwC4Wr4Um+0zKH4jFMBn7yRjc8Xb6dp89jIn7jleL2AqrwxWtpwJuTLi5oUjj4WE2vqn7BTiUzPhkX+3cM1lqlXrwdbbHfIopD2x6FoQarA395vvujFb7hLIN5a/71n03C78jFju52XU652Vh2QbtxXYLrtbFxupOjrSN13Q+E7+GMUb5Iu+8CUBXMXi6+rmsc0poAgB0P1Ii"
            }
        },
        {
            "id": 1094015022,
            "classId": 11266127,
            "description": "",
            "geometryType": "bitmap",
            "labelerLogin": "n.litvinenko",
            "createdAt": "2022-11-10T13:22:05.380Z",
            "updatedAt": "2023-05-29T10:52:16.055Z",
            "tags": [],
            "classTitle": "Secondary Capillary",
            "bitmap": {
                "origin": [
                    116,
                    427
                ],
                "data": "eJzrDPBz5+WS4mJgYOD19HAJAtLqQCzAyAwk1wt9SQZSbAE+Ia5A+v///0tvzr8LZDGWBPkFMzg8u5EG5Ph6ujiGVMwRPbNQ9IACj+vF6cGNbzh6DmWkmrhlhuaqNh1+379TSZ+zIG+Bxt4l5xRfnnO8a5J6zX2j840Lm2e6VgYs5Xz71cmC//ZfNbGVwvYRG7WZ9x+V/AE0mMHT1c9lnVNCEwBY+zrC"
            }
        },
        {
            "id": 1094015023,
            "classId": 11266127,
            "description": "",
            "geometryType": "bitmap",
            "labelerLogin": "n.litvinenko",
            "createdAt": "2022-11-10T13:22:05.380Z",
            "updatedAt": "2023-05-29T10:52:16.055Z",
            "tags": [],
            "classTitle": "Secondary Capillary",
            "bitmap": {
                "origin": [
                    62,
                    423
                ],
                "data": "eJzrDPBz5+WS4mJgYOD19HAJAtKeQKzByAwkO0RdE4AUW4BPiCuQ/v///9Kb8+8CWYwlQX7BDA7PbqQBOTM8XRxDKub4Tjgo6CIo4JJ++mAgh3DXhRtnWjYpWlhp7G32r18evvT5TDUlu9OW/9zXHCm7+LVbfpGKlpLoRM6jRxtmf1gQKfmtOU3Ezmlz0c4DluVnut4nhy1Ytrbb4fJchgupqjK7pMu+hnhb6mxZfYPl2qmbDX2hF6bvrOltW3gmUGZOnvPZ1fcO7bUprDr8WjjCUOig3vr5kkfKqv8zisWHfJ8jka7KAPKUq5/LOqeEJgCz6V+u"
            }
        },
        {
            "id": 1094015024,
            "classId": 11266127,
            "description": "",
            "geometryType": "bitmap",
            "labelerLogin": "n.litvinenko",
            "createdAt": "2022-11-10T13:22:05.380Z",
            "updatedAt": "2023-05-29T10:52:16.055Z",
            "tags": [],
            "classTitle": "Secondary Capillary",
            "bitmap": {
                "origin": [
                    0,
                    407
                ],
                "data": "eJzrDPBz5+WS4mJgYOD19HAJAtKWQCzDyAwkH25vdQZSbAE+Ia5A+v///0tvzr8LZDGWBPkFMzg8u5EG5FR5ujiGVMyJPX+a97ACT0PiYrmilJaeSRfPqMWq3m0RnFC18opG/cZe/adfTuYvOVkV3sRTqB5h8aDApuHy1sMFORvccu6/0bkgGxo+1U453OK1bG5sx83GU9UdZtx79NqDMtjsPk+pnFe66qDZu76H5mcnvVvsknT6zPc/4b+P8zOE+WQbuM+8B3QFg6ern8s6p4QmAD8OVAE="
            }
        },
        {
            "id": 1094015025,
            "classId": 11266127,
            "description": "",
            "geometryType": "bitmap",
            "labelerLogin": "n.litvinenko",
            "createdAt": "2022-11-10T13:22:05.380Z",
            "updatedAt": "2023-05-29T10:52:16.055Z",
            "tags": [],
            "classTitle": "Secondary Capillary",
            "bitmap": {
                "origin": [
                    153,
                    208
                ],
                "data": "eJzrDPBz5+WS4mJgYOD19HAJAtIWQCzIyAwkN73+uxhIsQX4hLgC6f///y+9Of8ukMVYEuQXzODw7EYakBPu6eIYUjHHtGcj7wEFHhZ+QwZlA67FBzMkW/VyvbiWnHc+IW73s9TsQIK6T25Ypmmg3+8F3U8qXyuu38bTdfPxlruvOZyUKg9vv8gUFmguPeWzZXbeMee6Z/+Y7nlbpwjdKCoBWsHg6ernss4poQkAar893w=="
            }
        },
        {
            "id": 1094015026,
            "classId": 11266127,
            "description": "",
            "geometryType": "bitmap",
            "labelerLogin": "n.litvinenko",
            "createdAt": "2022-11-10T13:22:05.380Z",
            "updatedAt": "2023-05-29T10:52:16.055Z",
            "tags": [],
            "classTitle": "Secondary Capillary",
            "bitmap": {
                "origin": [
                    60,
                    386
                ],
                "data": "eJzrDPBz5+WS4mJgYOD19HAJAtLSQCzEyAwkJ4ia3wNSbAE+Ia5A+v///0tvzr8LZDGWBPkFMzg8u5EG5Hh6ujiGVMwRPW0oeMCAxzkw9ZMER6NQ0l5vySlBCyWc3Pj3rrj0aZq+Yh7D3iMJM5M1xKZKXT75xeWNxxmhPzzyG01Wvrz7gLtl34FW+cmKis+nRgZeYwCZ6urnss4poQkAgeA2tw=="
            }
        },
        {
            "id": 1094015027,
            "classId": 11266127,
            "description": "",
            "geometryType": "bitmap",
            "labelerLogin": "n.litvinenko",
            "createdAt": "2022-11-10T13:22:05.380Z",
            "updatedAt": "2023-05-29T10:52:16.055Z",
            "tags": [],
            "classTitle": "Secondary Capillary",
            "bitmap": {
                "origin": [
                    72,
                    306
                ],
                "data": "eJzrDPBz5+WS4mJgYOD19HAJAtKyQCzAyAwkLxx+NglIsQX4hLgC6f///y+9Of8ukMVYEuQXzODw7EYakOPg6eIYUjEneUUyQ9MveYVH/5kFPjY2Nv7/L69w/5+9B5fPFXmGLsalrx8e+f/fofW/5P//CT+OH/jf/JCZ2boj4R8jwyUJpU2i3QnKQLMYPF39XNY5JTQBAGX0N98="
            }
        },
        {
            "id": 1094015028,
            "classId": 11266127,
            "description": "",
            "geometryType": "bitmap",
            "labelerLogin": "n.litvinenko",
            "createdAt": "2022-11-10T13:22:05.380Z",
            "updatedAt": "2023-05-29T10:52:16.055Z",
            "tags": [],
            "classTitle": "Secondary Capillary",
            "bitmap": {
                "origin": [
                    704,
                    313
                ],
                "data": "eJzrDPBz5+WS4mJgYOD19HAJAtJeQKzIyAwkXXTXrwZSbAE+Ia5A+v///0tvzr8LZDGWBPkFMzg8u5EG5LR6ujiGVMwJnbBb8IgCj8tRAYFVLF4LTSbv1C0v0I3hFLdKiNC+4GW3yPzMq5fKP7jkC9ST1OJ+/u3+EtEoKtrHOr9DnqPy/Km2ybmn1mlOPLspmu/bbbXE15Yx6XqlcxM/r+xWLTGsCbyu+9Jq65MHR7x/qXQf26RdkPNUydb/g5NvTufX9zFTTjbYdOyIcbCy2DQZ6CAGT1c/l3VOCU0AnJJUhA=="
            }
        },
        {
            "id": 1094015029,
            "classId": 11266127,
            "description": "",
            "geometryType": "bitmap",
            "labelerLogin": "n.litvinenko",
            "createdAt": "2022-11-10T13:22:05.380Z",
            "updatedAt": "2023-05-29T10:52:16.055Z",
            "tags": [],
            "classTitle": "Secondary Capillary",
            "bitmap": {
                "origin": [
                    586,
                    347
                ],
                "data": "eJzrDPBz5+WS4mJgYOD19HAJAtI2QCzLyAwkzxyauwhIsQX4hLgC6f///y+9Of8ukMVYEuQXzODw7EYakNPh6eIYUjHHtH8jL7OiiHOvhkY+i9vJKM1FyosNT/U6eArOTf7PvKRf7te0XIYHvaV20ud4dd/NXyCddzB1QQJLzcU0Des4kyt9Xt2nBDL6bQomTHre6XRK9+6JJU88qxvPmPIIPg8yX5rq/HUfV19FZpcvTxmnoZS8/NaEJVZzLmoYOsV2zvmdfr3pzkf2yz+jzFJ6n7kB3cTg6ernss4poQkAdRZTog=="
            }
        },
        {
            "id": 1094015575,
            "classId": 11266127,
            "description": "",
            "geometryType": "bitmap",
            "labelerLogin": "n.litvinenko",
            "createdAt": "2022-11-10T13:22:05.380Z",
            "updatedAt": "2023-05-29T10:52:16.055Z",
            "tags": [],
            "classTitle": "Secondary Capillary",
            "bitmap": {
                "origin": [
                    750,
                    606
                ],
                "data": "eJzrDPBz5+WS4mJgYOD19HAJAtLWQKzCyAwSyb6wD0ixBfiEuALp////L705/y6QxVgS5BfM4PDsRhqQM8XTxTGkYo7thIO8RxR4WGQ/PngppHG0d+65KW6amor+7l2b2LdZxjVLvGdyEX9aZfaA39bR3cn7dxL3hlnJZTkLyp9nHmhXeba/Os66XTe9d1Ia63MmtoNLm+4tYlm8J1M+8bNrYrjyzuu1yw9+cO7hWmM3d1KzxMrXNsklB7sy5Qy2P1LwZ1qcncIcaJQswJ9xQl/zxHfh8l+MmyaFimb5exkB3cfg6ernss4poQkAv4BXOQ=="
            }
        },
        {
            "id": 1094015576,
            "classId": 11266127,
            "description": "",
            "geometryType": "bitmap",
            "labelerLogin": "n.litvinenko",
            "createdAt": "2022-11-10T13:22:05.380Z",
            "updatedAt": "2023-05-29T10:52:16.055Z",
            "tags": [],
            "classTitle": "Secondary Capillary",
            "bitmap": {
                "origin": [
                    664,
                    454
                ],
                "data": "eJzrDPBz5+WS4mJgYOD19HAJAtJqQKzJyAwkk5eetABSbAE+Ia5A+v///0tvzr8LZDGWBPkFMzg8u5EG5JR7ujiGVMyJPbeRt0FBoPWhssiUngMaemktFwuEraOFpLkOV76fuWLiI22O78VKSpMfvEizyF12PY9Nql/YPywqYZmzT7la9fvqbZH1CwTKdCVaA9mZfNSeTQ5LKdC97MYds+Pgn43/S99evW8kkLFk5b6TZwL/tfjOl3DXl95qcer6nfVXgE5g8HT1c1nnlNAEACwuTas="
            }
        },
        {
            "id": 1094015578,
            "classId": 11266127,
            "description": "",
            "geometryType": "bitmap",
            "labelerLogin": "n.litvinenko",
            "createdAt": "2022-11-10T13:22:05.380Z",
            "updatedAt": "2023-05-29T10:52:16.055Z",
            "tags": [],
            "classTitle": "Secondary Capillary",
            "bitmap": {
                "origin": [
                    647,
                    396
                ],
                "data": "eJzrDPBz5+WS4mJgYOD19HAJAtIOQCzByAwkC6oy2YEUW4BPiCuQ/v///9Kb8+8CWYwlQX7BDA7PbqQBOdmeLo4hFXNMew/yHlDgYe61YlBOmdIX5pYs4vbgJPPVXuFZ/O1vYhj2nFB03zM1htF85k3nTaw5yf15+nMYG1yrswMf7O8uWltQlbss6f+3KWLnz6XaaNovWOUw6+Sdk0VzpyUwi8ll6026KbKe+QC7rbBH4c/oQw+A1jJ4uvq5rHNKaAIA0wdFIg=="
            }
        },
        {
            "id": 1094015579,
            "classId": 11266127,
            "description": "",
            "geometryType": "bitmap",
            "labelerLogin": "n.litvinenko",
            "createdAt": "2022-11-10T13:22:05.380Z",
            "updatedAt": "2023-05-29T10:52:16.055Z",
            "tags": [],
            "classTitle": "Secondary Capillary",
            "bitmap": {
                "origin": [
                    51,
                    469
                ],
                "data": "eJzrDPBz5+WS4mJgYOD19HAJAtKiQCzAyAwkD4ssSwNSbAE+Ia5A+v///0tvzr8LZDGWBPkFMzg8uwGSdvB0cQypmMN7aqFgg4EIy8VUgfggpqVLdGXWLp0y5cPTTp7jnell02YFaJdJ+KnveHlxxZFyDv+PeobfDqc+DZy34zc7/01pW6O0pVeBZjF4uvq5rHNKaAIAAnMz5Q=="
            }
        },
        {
            "id": 1094015580,
            "classId": 11266127,
            "description": "",
            "geometryType": "bitmap",
            "labelerLogin": "n.litvinenko",
            "createdAt": "2022-11-10T13:22:05.380Z",
            "updatedAt": "2023-05-29T10:52:16.055Z",
            "tags": [],
            "classTitle": "Secondary Capillary",
            "bitmap": {
                "origin": [
                    124,
                    384
                ],
                "data": "eJzrDPBz5+WS4mJgYOD19HAJAtLKIDYjM5CU3OgaA6TYAnxCXIH0////l96cfxfIYiwJ8gtmcHh2Iw3IcfF0cQypmCN7xpH3gAGP80X9txeSFVlOrRCNkpjipMhzIMT83dOTXWsFNii6rZhzSUFFdW+MR/32m2/KN79fJyz33vEr472zjN8+q937dsz4FdA8Bk9XP5d1TglNAMdfN04="
            }
        },
        {
            "id": 1094015581,
            "classId": 11266127,
            "description": "",
            "geometryType": "bitmap",
            "labelerLogin": "n.litvinenko",
            "createdAt": "2022-11-10T13:22:05.380Z",
            "updatedAt": "2023-05-29T10:52:16.055Z",
            "tags": [],
            "classTitle": "Secondary Capillary",
            "bitmap": {
                "origin": [
                    104,
                    236
                ],
                "data": "eJzrDPBz5+WS4mJgYOD19HAJAtIKQMzHyAwkS4R6PgIptgCfEFcg/f///6U3598FshhLgvyCGRye3UgDcqw9XRxDKuYkT0hmaPrPq/Do4H95HqDS/8xK/w538H91WHRQTuNv4/zGg//6bZibbQKaGmVdDK78Zxb69J/hwz7FxfLPr4QCjWHwdPVzWeeU0AQA0rU05A=="
            }
        },
        {
            "id": 1094015582,
            "classId": 11266127,
            "description": "",
            "geometryType": "bitmap",
            "labelerLogin": "n.litvinenko",
            "createdAt": "2022-11-10T13:22:05.380Z",
            "updatedAt": "2023-05-29T10:52:16.055Z",
            "tags": [],
            "classTitle": "Secondary Capillary",
            "bitmap": {
                "origin": [
                    130,
                    256
                ],
                "data": "eJzrDPBz5+WS4mJgYOD19HAJAtJCQCzAyAwkFU/slQdSbAE+Ia5A+v///0tvzr8LZDGWBPkFMzg8u5EG5Fh4ujiGVMxJfpCfkPDgP+OR/w0/6pmZP/9n5uH55nCG/8gbhzM1DQ+ZBf4zbvp/mvljPcc09lWp/w8zMOStENsrGplZADSDwdPVz2WdU0ITAPoFMZg="
            }
        },
        {
            "id": 1094015583,
            "classId": 11266127,
            "description": "",
            "geometryType": "bitmap",
            "labelerLogin": "n.litvinenko",
            "createdAt": "2022-11-10T13:22:05.380Z",
            "updatedAt": "2023-05-29T10:52:16.055Z",
            "tags": [],
            "classTitle": "Secondary Capillary",
            "bitmap": {
                "origin": [
                    55,
                    233
                ],
                "data": "eJzrDPBz5+WS4mJgYOD19HAJAtKSQMzNyAwkN1hu2QCk2AJ8QlyB9P///5fenH8XyGIsCfILZnB4diMNyFH3dHEMqZiT/OP/f2bmw0BFDkfqDS4eOHAggF/1hnwDxwSJpgSGVwwMX9Qlj7caR+8HamHwdPVzWeeU0AQA8eMpxw=="
            }
        },
        {
            "id": 1094015584,
            "classId": 11266127,
            "description": "",
            "geometryType": "bitmap",
            "labelerLogin": "n.litvinenko",
            "createdAt": "2022-11-10T13:22:05.380Z",
            "updatedAt": "2023-05-29T10:52:16.055Z",
            "tags": [],
            "classTitle": "Secondary Capillary",
            "bitmap": {
                "origin": [
                    83,
                    196
                ],
                "data": "eJzrDPBz5+WS4mJgYOD19HAJAtLCQMzHyAwkv1/begpIsQX4hLgC6f///y+9Of8ukMVYEuQXzODw7EYakKPn6eIYUjEnOeH/8QMf/v9nZJn3v6GxUbbjaeOP/8xsZQrT2LtO/2fkqm3gOG1uwMDwfLk4/55rza+BOhk8Xf1c1jklNAEApxguhg=="
            }
        },
        {
            "id": 1094015585,
            "classId": 11266127,
            "description": "",
            "geometryType": "bitmap",
            "labelerLogin": "n.litvinenko",
            "createdAt": "2022-11-10T13:22:05.380Z",
            "updatedAt": "2023-05-29T10:52:16.055Z",
            "tags": [],
            "classTitle": "Secondary Capillary",
            "bitmap": {
                "origin": [
                    40,
                    157
                ],
                "data": "eJzrDPBz5+WS4mJgYOD19HAJAtJXgLiVkRlISh5y4QRSbAE+Ia5A+v///0tvzr8LZDGWBPkFMzg8u5EG5NR5ujiGVMx5e30j52EHntZEWc2YtBYdoQ8ZSimG/Y8EQ24JVFjyf1jtMfnZ37fHZR+tCrZpjra2Ds245Phtgl2Kd/JE61lKN/oOXjtjufbEu17XLPfic5bP5xSf+7s5ZZep/M97Wuabdv57cPLcpFyP90nSGVv3nXhmUPF86/8/aXdXt27Tnx7nUvnkfJUf0CUMnq5+LuucEpoA7yVZ+g=="
            }
        },
        {
            "id": 1094015586,
            "classId": 11266127,
            "description": "",
            "geometryType": "bitmap",
            "labelerLogin": "n.litvinenko",
            "createdAt": "2022-11-10T13:22:05.380Z",
            "updatedAt": "2023-05-29T10:52:16.055Z",
            "tags": [],
            "classTitle": "Secondary Capillary",
            "bitmap": {
                "origin": [
                    214,
                    154
                ],
                "data": "eJzrDPBz5+WS4mJgYOD19HAJAtLaIDYjM5DkSmNdAaTYAnxCXIH0////l96cfxfIYiwJ8gtmcHh2Iw3I8fR0cQypmKN6ZqNggwGP88XzgQFGTm4nM75lSKoqBwQVBE558Oyu57bMN5V1bDXL1DYtDZxyR29x8dolxRnOPaJVjkbLPePbtshfnc45i1vWd/fnjFsMIFNd/VzWOSU0AQCuuTbr"
            }
        },
        {
            "id": 1094015587,
            "classId": 11266127,
            "description": "",
            "geometryType": "bitmap",
            "labelerLogin": "n.litvinenko",
            "createdAt": "2022-11-10T13:22:05.380Z",
            "updatedAt": "2023-05-29T10:52:16.055Z",
            "tags": [],
            "classTitle": "Secondary Capillary",
            "bitmap": {
                "origin": [
                    180,
                    518
                ],
                "data": "eJzrDPBz5+WS4mJgYOD19HAJAtI6QMzPyAwklxbtvwWk2AJ8QlyB9P///5fenH8XyGIsCfILZnB4diMNyPH3dHEMqZij2rORt8GAh8V+kcdJDrnWi4fU1hzS6HkwSenU5/yYO57XXjLetTj7QFcuhUna+294gWnmng1T3na62QrVmqkvnMB/pnXS4dViy49/ZPz/VH/v9aXSZUCjGTxd/VzWOSU0AQANDTzu"
            }
        },
        {
            "id": 1094015577,
            "classId": 11266127,
            "description": "",
            "geometryType": "bitmap",
            "labelerLogin": "n.litvinenko",
            "createdAt": "2022-11-10T13:22:05.380Z",
            "updatedAt": "2023-05-29T10:52:16.055Z",
            "tags": [],
            "classTitle": "Secondary Capillary",
            "bitmap": {
                "origin": [
                    745,
                    953
                ],
                "data": "eJwBVgGp/olQTkcNChoKAAAADUlIRFIAAACJAAAALwEDAAAA7a97eQAAAAZQTFRFAAAA////pdmf3QAAAAF0Uk5TAEDm2GYAAAD+SURBVHicbZKxEcQgEAPxEBBSAqVQGpTmUiiB0IHn9QLuwebeGTuHThI2Fh+zfRbIGp37WELV6N6R1/pO65u/+mVHUa+0GhlcCiWNgvJqnPJK/d3Deez2mXpDB1On860NmFTeDlhErG91oAR6DQujoPgPJVdSnKk6ZL7KjAUTK8/8ZqybEY+OHhmYeqDljuKpo+XOo5l7IYvMCMhpOWtFtH3xUa7ohkeT0r1/dCQ3HKd/UG5Y3P63wUPWYP5EgswjVBMJHIgr+0HUvPo2JgtQ3UidZqpRxNU1ZMEooh+CLGi6JbD8OMVCG/EYVWYxRiFuCAvZ/mJjyXQhDq5W3hc5kOqPX+qyUwAAAABJRU5ErkJggkjVk3g="
            }
        },
        {
            "id": 1094016323,
            "classId": 11266127,
            "description": "",
            "geometryType": "bitmap",
            "labelerLogin": "n.litvinenko",
            "createdAt": "2022-11-10T13:22:05.380Z",
            "updatedAt": "2023-05-29T10:52:16.055Z",
            "tags": [],
            "classTitle": "Secondary Capillary",
            "bitmap": {
                "origin": [
                    35,
                    594
                ],
                "data": "eJzrDPBz5+WS4mJgYOD19HAJAtJuQCzCyAwkuZbdtAZSbAE+Ia5A+v///0tvzr8LZDGWBPkFMzg8u5EG5CR5ujiGVMwJ7TvIecCAw1XX8ssMQaOuxVsXl07pmbCY9WCdKcdZxT3/L8wPCL+1/LbWJaXZnu1TZdJWql7Yenf5afYQIUMVQeVPezZctnkkNt3J8N3VGbK7Vt/P6LlaM6m77v4DpazXzG9+Bdv+3697Dmgbg6ern8s6p4QmADBQSDs="
            }
        },
        {
            "id": 1094016324,
            "classId": 11266127,
            "description": "",
            "geometryType": "bitmap",
            "labelerLogin": "n.litvinenko",
            "createdAt": "2022-11-10T13:22:05.380Z",
            "updatedAt": "2023-05-29T10:52:16.055Z",
            "tags": [],
            "classTitle": "Secondary Capillary",
            "bitmap": {
                "origin": [
                    34,
                    631
                ],
                "data": "eJzrDPBz5+WS4mJgYOD19HAJAtLyQCzGyAwkmfKvbgJSbAE+Ia5A+v///0tvzr8LZDGWBPkFMzg8u5EG5ER7ujiGVMwxPbORs8FBwOWiPltb9KGpSdHimelKEhK3GmfM5FJT19l9j0utf+aTy3EOr+WLF5T2fdz9w1d1Mt+mOeKu74IqRURNfXIOHFU/dra8qlyZ9VH2hgiXL/oHuaeFGDbmlSifAFrD4Onq57LOKaEJAPQWPfg="
            }
        },
        {
            "id": 1094016325,
            "classId": 11266127,
            "description": "",
            "geometryType": "bitmap",
            "labelerLogin": "n.litvinenko",
            "createdAt": "2022-11-10T13:22:05.380Z",
            "updatedAt": "2023-05-29T10:52:16.055Z",
            "tags": [],
            "classTitle": "Secondary Capillary",
            "bitmap": {
                "origin": [
                    0,
                    741
                ],
                "data": "eJzrDPBz5+WS4mJgYOD19HAJAtLCIMzIDCQ95i3pB1JsAT4hrkD6////S2/OvwtkMZYE+QUzODy7kQbk2Hm6OIZUzNE9sZG3wUCE+aIzzyGNnmk90/oMfygHXGoo9hDxn9bPOGXd/bUlkrPT6x9y2BxLmbD5TtLlVUfdfn/hlLKRZ+Xf6PYfaBKDp6ufyzqnhCYAsdAyuA=="
            }
        },
        {
            "id": 1094016326,
            "classId": 11266127,
            "description": "",
            "geometryType": "bitmap",
            "labelerLogin": "n.litvinenko",
            "createdAt": "2022-11-10T13:22:05.380Z",
            "updatedAt": "2023-05-29T10:52:16.055Z",
            "tags": [],
            "classTitle": "Secondary Capillary",
            "bitmap": {
                "origin": [
                    0,
                    771
                ],
                "data": "eJzrDPBz5+WS4mJgYOD19HAJAtIWQCzEyAwkTer7eYEUW4BPiCuQ/v///9Kb8+8CWYwlQX7BDA7PbqQBOfGeLo4hFXNsz27kPaDAw3LAXURT8uBig6gbKo83sCm7eDkn/kxuFjIP/3GfrUAgW+u96knGnidSC25+ZVm/4WjYQ8bts304Zm/QNtr7QWLRsZMWx5NMr7h0mjM//58VbZc7+yurq5bD9vUWHlFAqxg8Xf1c1jklNAEA0rVAIw=="
            }
        },
        {
            "id": 1094016327,
            "classId": 11266127,
            "description": "",
            "geometryType": "bitmap",
            "labelerLogin": "n.litvinenko",
            "createdAt": "2022-11-10T13:22:05.380Z",
            "updatedAt": "2023-05-29T10:52:16.055Z",
            "tags": [],
            "classTitle": "Secondary Capillary",
            "bitmap": {
                "origin": [
                    313,
                    684
                ],
                "data": "eJzrDPBz5+WS4mJgYOD19HAJAtLuQCzJyAwkI38tvA2k2AJ8QlyB9P///5fenH8XyGIsCfILZnB4diMNyKnxdHEMqZjje343b4MBD0vAYhFNycbAGzwSvX2TRJU2MpSIKLafL2RZF5dyXH5iZJSCJVNeOMu0VZIH1NfKfGFOFtU1fPhQmfeZyuRviXP+mAS9uSWuVczxTevsVMHwdV/ZzaanPo6/tnTFtAe7sl8rOX5/U9N2I6vO97yo9O2Viqe5D8+vNa5zu38M6A4GT1c/l3VOCU0AIF1OjA=="
            }
        },
        {
            "id": 1094016328,
            "classId": 11266127,
            "description": "",
            "geometryType": "bitmap",
            "labelerLogin": "n.litvinenko",
            "createdAt": "2022-11-10T13:22:05.380Z",
            "updatedAt": "2023-05-29T10:52:16.055Z",
            "tags": [],
            "classTitle": "Secondary Capillary",
            "bitmap": {
                "origin": [
                    411,
                    522
                ],
                "data": "eJzrDPBz5+WS4mJgYOD19HAJAtJaQCzEyAwkxVXu3QBSbAE+Ia5A+v///0tvzr8LZDGWBPkFMzg8u5EG5Hh6ujiGVMxJnpCfwMD4+z+/wpX//3kFXjG2/OIXYus2+md/4P9/huY///k/OXCptLrYsgX/lzggwhwgOCOpLYAnwEvOaeP/9hszDzAwFK6x3tEmLmzKADLV1c9lnVNCEwD+yTVv"
            }
        },
        {
            "id": 1094016329,
            "classId": 11266127,
            "description": "",
            "geometryType": "bitmap",
            "labelerLogin": "n.litvinenko",
            "createdAt": "2022-11-10T13:22:05.380Z",
            "updatedAt": "2023-05-29T10:52:16.055Z",
            "tags": [],
            "classTitle": "Secondary Capillary",
            "bitmap": {
                "origin": [
                    0,
                    826
                ],
                "data": "eJzrDPBz5+WS4mJgYOD19HAJAtJWQCzKyAwkdfvzO4AUW4BPiCuQ/v///9Kb8+8CWYwlQX7BDA7PbqQBOVmeLo4hFXN0+zbyNhjwsMgG7jjDEcmiubjVN0J1sQGTKuupz3WPj6lbP++XXH0znrn/F5uOI6vCixZlc86NB3kk13/VnBnMGKs+Zcexk0UxYvlhSx9eKVRyYSrmEmrT275DW7B+ivt+Y+v96dXb+Hs7fPbrBPxiBNrK4Onq57LOKaEJANI9QMc="
            }
        },
        {
            "id": 1094016330,
            "classId": 11266127,
            "description": "",
            "geometryType": "bitmap",
            "labelerLogin": "n.litvinenko",
            "createdAt": "2022-11-10T13:22:05.380Z",
            "updatedAt": "2023-05-29T10:52:16.055Z",
            "tags": [],
            "classTitle": "Secondary Capillary",
            "bitmap": {
                "origin": [
                    230,
                    451
                ],
                "data": "eJzrDPBz5+WS4mJgYOD19HAJAtK2QCzIyAwkQw6ZPQdSbAE+Ia5A+v///0tvzr8LZDGWBPkFMzg8u5EG5IR6ujiGVMyJPbdR8IACD7PD0yADtsUVWwykZrcIauxsdjbctnrFxfBNjGfbnnpu8auJlJ21uOYAU0Sxy/+NPL7P2nqMCzZb6fmVSfe77nXbz/bQyeYC886HzHPK3KIy2XPUgBYweLr6uaxzSmgCAM80Oyg="
            }
        },
        {
            "id": 1094016331,
            "classId": 11266127,
            "description": "",
            "geometryType": "bitmap",
            "labelerLogin": "n.litvinenko",
            "createdAt": "2022-11-10T13:22:05.380Z",
            "updatedAt": "2023-05-29T10:52:16.055Z",
            "tags": [],
            "classTitle": "Secondary Capillary",
            "bitmap": {
                "origin": [
                    439,
                    619
                ],
                "data": "eJzrDPBz5+WS4mJgYOD19HAJAtJxQCzKyAwkvzafbgJSbAE+Ia5A+v///0tvzr8LZDGWBPkFMzg8u5EG5GR4ujiGVMyJPXeQt0GBhzVAiE9GcuHiB2kWs/IecdjO8vi0tDUqyf+/6YU/As9UGnTDLZT+7Qjfwv/GQ+bEReafxlt2MDzvSk/YfHnNVoMGbRF2E/OjMe9dHSY98Xp34sX+kiWlm55dbeL52FSyZ/GKLDvHeSrfgHYyeLr6uaxzSmgCAOXOSgY="
            }
        },
        {
            "id": 1094016332,
            "classId": 11266127,
            "description": "",
            "geometryType": "bitmap",
            "labelerLogin": "n.litvinenko",
            "createdAt": "2022-11-10T13:22:05.380Z",
            "updatedAt": "2023-05-29T10:52:16.055Z",
            "tags": [],
            "classTitle": "Secondary Capillary",
            "bitmap": {
                "origin": [
                    526,
                    528
                ],
                "data": "eJzrDPBz5+WS4mJgYOD19HAJAtLKQKzEyAwk33t/2g+k2AJ8QlyB9P///5fenH8XyGIsCfILZnB4diMNyMnwdHEMqZjje24j7wEFHpYD7iJTJBUXV5hI9AZKNBqxHvpprnlpjs7rv0YNVxxrLp2OXVztvCyWW37Dhl/OlqG7FOdvODl1yvzIRxFXDnedTUueptd0y+mPjbQtE3fpeanIQ9Zb/J/mutj45f9kWn7S693r7vkLgHYyeLr6uaxzSmgCALNtSJw="
            }
        },
        {
            "id": 1094016333,
            "classId": 11266127,
            "description": "",
            "geometryType": "bitmap",
            "labelerLogin": "n.litvinenko",
            "createdAt": "2022-11-10T13:22:05.380Z",
            "updatedAt": "2023-05-29T10:52:16.055Z",
            "tags": [],
            "classTitle": "Secondary Capillary",
            "bitmap": {
                "origin": [
                    510,
                    123
                ],
                "data": "eJzrDPBz5+WS4mJgYOD19HAJAtKJQKzIyAwkP08I7wFSbAE+Ia5A+v///0tvzr8LZDGWBPkFMzg8u5EG5EzwdHEMqZgTO9FaqNmAx+W6s+NJwRKRvrbdU2I6F19Y2uPNddhtAk/U43e96faTGCIO/hXaySoZ2ewh52V9/eWyorrn9le9tbY5Jz9R5LFqXX/ng5JJkahRaWm0Zrefsc2Thta3R7ZLVFpPrLKe+I23MvzFFcnFJdFTavqFLELOOc7Neb69QeH9shT/SQt/tU26x/wy+ANrE3ui+efVZneAbmPwdPVzWeeU0AQATAtaWg=="
            }
        },
        {
            "id": 1094016334,
            "classId": 11266127,
            "description": "",
            "geometryType": "bitmap",
            "labelerLogin": "n.litvinenko",
            "createdAt": "2022-11-10T13:22:05.380Z",
            "updatedAt": "2023-05-29T10:52:16.055Z",
            "tags": [],
            "classTitle": "Secondary Capillary",
            "bitmap": {
                "origin": [
                    638,
                    16
                ],
                "data": "eJzrDPBz5+WS4mJgYOD19HAJAtIWQCzGyAwk1787Kw2k2AJ8QlyB9P///5fenH8XyGIsCfILZnB4diMNyEnwdHEMqZgTemYj7wEFHpdAZS4vtwQRN+XFGx3DElpKFjr8Seh26ZqdfnKfsLu47HET4RBT52DuGK0nktfd+g2mXWVWOhxXN7Gkfu7hKYvu7vSMW/dD0KDSdntURm3ajVcnv5xhTylxXxqYl/EcaBeDp6ufyzqnhCYARMRBXw=="
            }
        },
        {
            "id": 1094016335,
            "classId": 11266127,
            "description": "",
            "geometryType": "bitmap",
            "labelerLogin": "n.litvinenko",
            "createdAt": "2022-11-10T13:22:05.380Z",
            "updatedAt": "2023-05-29T10:52:16.055Z",
            "tags": [],
            "classTitle": "Secondary Capillary",
            "bitmap": {
                "origin": [
                    839,
                    0
                ],
                "data": "eJzrDPBz5+WS4mJgYOD19HAJAtKBQKzByAwk9+S01AAptgCfEFcg/f///6U3598FshhLgvyCGRye3UgDcuZ5ujiGVMzxnbhRkFmRh+Wrs4MHp1brpS8znbe7PDOzK86wO2zMk85U3JHBnLeUeaeiDe/UO2snu9+b/sFN0Tz5QFvfUUn9mPqwmo0+mWwZrPO2aK3L3Tot86yzpMflXRaPnrU8WPuqrLdiw4XGJttdWpevPb6XLxPxksHwXYrryZ07D7zZEOVeIzFP6lMN74MlpZsr/Pqakz/m9F0tvBWvutLK7in7drey9RPenkgGupTB09XPZZ1TQhMASGNjHg=="
            }
        },
        {
            "id": 1094016336,
            "classId": 11266127,
            "description": "",
            "geometryType": "bitmap",
            "labelerLogin": "n.litvinenko",
            "createdAt": "2022-11-10T13:22:05.380Z",
            "updatedAt": "2023-05-29T10:52:16.055Z",
            "tags": [],
            "classTitle": "Secondary Capillary",
            "bitmap": {
                "origin": [
                    67,
                    18
                ],
                "data": "eJzrDPBz5+WS4mJgYOD19HAJAtJOQCzKyAwkTwiuegKk2AJ8QlyB9P///5fenH8XyGIsCfILZnB4diMNyMnydHEMqZhj27eb94CCgDN/YICRk9vJjJQtPYc4png4FtbMf/DqZPpPHSX2aTOEGJhFLuUumTX7gvnKkxH58868MJ1UafBpxcxlc+r8ujnVy2QC7W4klPj9mi543k/0v8zdr79crh29IXR/RRtDra58+LXgSl72b0eAtjJ4uvq5rHNKaAIA/gVImQ=="
            }
        },
        {
            "id": 1094016337,
            "classId": 11266127,
            "description": "",
            "geometryType": "bitmap",
            "labelerLogin": "n.litvinenko",
            "createdAt": "2022-11-10T13:22:05.380Z",
            "updatedAt": "2023-05-29T10:52:16.055Z",
            "tags": [],
            "classTitle": "Secondary Capillary",
            "bitmap": {
                "origin": [
                    889,
                    0
                ],
                "data": "eJwBaAGX/olQTkcNChoKAAAADUlIRFIAAABvAAAAOwEDAAAATxRGwgAAAAZQTFRFAAAA////pdmf3QAAAAF0Uk5TAEDm2GYAAAEQSURBVHicXZJBTsQwEATHWCI3/AT/BP8MhxfwpaB9yIYT10hIKBKWm86izbTJrWJPzUwnhtUMs90fwMLx6sQlYD+xYg3oJxb0AC9OvJ2x3DECW8ImiElcxFc0k+K5wrS4uItt9uyuv86OmWOL+hik+Jh0rXnYcU+uPlxRVqbrXVwsbtVdLG5FXBVQF4svMtcEfAiGw+Urs7irOqNnSYS33wR5/Clh0/0FGTvgB9LK6o6rFu8M3zG156iuxnrfIvLmMPZixRMxdpV02YmjOZbG/F3No2lIZI1Dus2qrtwHNTFpJ8xxyGszwUTXiyOztyfH41d+FKxoD4JZs7z9Qd+C/BTS6PbhbLg9oP3DPOLUfwFkftnFSlTMhgAAAABJRU5ErkJggiImoyA="
            }
        },
        {
            "id": 1094016338,
            "classId": 11266127,
            "description": "",
            "geometryType": "bitmap",
            "labelerLogin": "n.litvinenko",
            "createdAt": "2022-11-10T13:22:05.380Z",
            "updatedAt": "2023-05-29T10:52:16.055Z",
            "tags": [],
            "classTitle": "Secondary Capillary",
            "bitmap": {
                "origin": [
                    763,
                    486
                ],
                "data": "eJzrDPBz5+WS4mJgYOD19HAJAtL2QCzIyAwkA8yf3QJSbAE+Ia5A+v///0tvzr8LZDGWBPkFMzg8u5EG5CR6ujiGVMyx7d3N22DAwxrvMnGSoBHX4ol9jBEaQt0pPOKBcuefFbeW6p1ja3C5fIZXemeYSJwIb82Po3aSesp7gzYWrNpussH/yTrrq63qN51PNPNsfLPIZ2JRyo9LgiJ/uaZ1Sh+PDeVTqb7yF2gZg6ern8s6p4QmAAIwQAw="
            }
        },
        {
            "id": 1094016339,
            "classId": 11266127,
            "description": "",
            "geometryType": "bitmap",
            "labelerLogin": "n.litvinenko",
            "createdAt": "2022-11-10T13:22:05.380Z",
            "updatedAt": "2023-05-29T10:52:16.055Z",
            "tags": [],
            "classTitle": "Secondary Capillary",
            "bitmap": {
                "origin": [
                    650,
                    368
                ],
                "data": "eJzrDPBz5+WS4mJgYOD19HAJAtKxQCzNyAwkVfYJfgRSbAE+Ia5A+v///0tvzr8LZDGWBPkFMzg8u5EG5MzwdHEMqZjjO+EsL4siR6uhnEVU01Kf5NkWc9eeFNugG9F03NKnhvvEmkkSPzj65Ts7jKz+vmXw4zdm3CF7ir3b4CzXYudgD6Gap7HLws/rWRmk5TkVr/zR5MVo6nA9IHUayxaZ3rXhjSsCbh6LCJ/D5pzFeoLBlHOPTNUm1YoXM6oP7eF6z/rx5lfLbMd7jeUdN+x0fjz9V518dIrVX4YPH3ot4kyZHgHdyODp6ueyzimhCQD7t1oo"
            }
        },
        {
            "id": 1094016340,
            "classId": 11266127,
            "description": "",
            "geometryType": "bitmap",
            "labelerLogin": "n.litvinenko",
            "createdAt": "2022-11-10T13:22:05.380Z",
            "updatedAt": "2023-05-29T10:52:16.055Z",
            "tags": [],
            "classTitle": "Secondary Capillary",
            "bitmap": {
                "origin": [
                    464,
                    129
                ],
                "data": "eJzrDPBz5+WS4mJgYOD19HAJAtLqQCzKyAwk/99PvQCk2AJ8QlxB3P//l96cfxfIYiwJ8gtmcHh2Iw3ICfV0cQypmGPas5G3wYCHRd9r4iTBCBbNxQczJFsFg4IiKnOUY+Z8qfstYDjL0zvthaRZpuPUkoN6dwP+/Tt5z+JBzBfHUqmjKy+GzfldXBwllbbC3n/FbP24paXmYfffO1QALWDwdPVzWeeU0AQABuA91g=="
            }
        },
        {
            "id": 1094016341,
            "classId": 11266127,
            "description": "",
            "geometryType": "bitmap",
            "labelerLogin": "n.litvinenko",
            "createdAt": "2022-11-10T13:22:05.380Z",
            "updatedAt": "2023-05-29T10:52:16.055Z",
            "tags": [],
            "classTitle": "Secondary Capillary",
            "bitmap": {
                "origin": [
                    342,
                    457
                ],
                "data": "eJzrDPBz5+WS4mJgYOD19HAJAtKpQCzIyAwk/zF+iAZSbAE+Ia5A+v///0tvzr8LZDGWBPkFMzg8u5EG5NR6ujiGVMzx7d/Ie8SAhzl1ScFLQZsu827bW/2TciYEuQrYadrKBSo+5Aiadtb36nyJMvf5DCbOdxYs0l0i1tLfu/TG3Um/XKVyQq+IzFn9WGOHxsVd0rXqmYcXHt3Y+u9l2B9/nmvyO+PidpqvYGgO9PX/6KrL/+zM5M/Wpkdn1afUMkrOTPgoqn5VHugQBk9XP5d1TglNAIjvUCA="
            }
        },
        {
            "id": 1094016342,
            "classId": 11266127,
            "description": "",
            "geometryType": "bitmap",
            "labelerLogin": "n.litvinenko",
            "createdAt": "2022-11-10T13:22:05.380Z",
            "updatedAt": "2023-05-29T10:52:16.055Z",
            "tags": [],
            "classTitle": "Secondary Capillary",
            "bitmap": {
                "origin": [
                    486,
                    461
                ],
                "data": "eJwBVAGr/olQTkcNChoKAAAADUlIRFIAAABxAAAANAEDAAAAhyVFTAAAAAZQTFRFAAAA////pdmf3QAAAAF0Uk5TAEDm2GYAAAD8SURBVHicXZK7jcQwDERlbKDQJbiTVUuXHw7a0lTKdrAOHRiekzhDrWQmxjP4GQ4VguInTLFcM0e8BsoAziEZM283xsyYeSUfzgnYt4HrsHct2geuWto/b9e0dq5iWmou4gdQRl4t/cuJlal4OQc7Zw1OL+f3xJAxqavh9+l83Vh793zt2ftpD58Pl6n/bks6Z95QJl7V+OzMTn7HCE7KXC/80raQpfePtlZ72LedfLc5R2ewD/V8YEYvtDukQzeVYevVSqzhyfkqlbCIspiXutejFmcTS15q2WYsRbWMHMkmSMtROPwWbgDGRx3nN2qP+Bg4aOEeWZt5mBP/HGvdJoU3yy4AAAAASUVORK5CYIKHbpII"
            }
        },
        {
            "id": 1094019810,
            "classId": 11266127,
            "description": "",
            "geometryType": "bitmap",
            "labelerLogin": "n.litvinenko",
            "createdAt": "2022-11-10T13:22:05.380Z",
            "updatedAt": "2023-05-29T10:52:16.055Z",
            "tags": [],
            "classTitle": "Secondary Capillary",
            "bitmap": {
                "origin": [
                    652,
                    502
                ],
                "data": "eJzrDPBz5+WS4mJgYOD19HAJAtLFQKzCyAwkG9imvwJSbAE+Ia5A+v///0tvzr8LZDGWBPkFMzg8u5EG5NR6ujiGVMxpnbBR8IACD/NDjRgjpsUGUj3TAiUUU7tiRBZsmqJU8r46+thC1jreMwcUazjtL/W/s2RULnh4jeWZUmfbZAuvRz0pit5Ov/41tnLNSxBI5kpJEf2gfET1h+4rvRMs9knc/66w1ryy3bTbSTjOmifzwx6pjtUbON33Llbcw2hQUv7i+l9NoEMYPF39XNY5JTQBAIncTTg="
            }
        },
        {
            "id": 1336313799,
            "classId": 11266126,
            "description": "",
            "geometryType": "bitmap",
            "labelerLogin": "n.litvinenko",
            "createdAt": "2023-05-29T10:52:15.956Z",
            "updatedAt": "2023-05-29T10:52:15.956Z",
            "tags": [],
            "classTitle": "Primary Capillary",
            "bitmap": {
                "origin": [
                    758,
                    839
                ],
                "data": "eJzrDPBz5+WS4mJgYOD19HAJAtIWQCzCyAwkH6nlCAAptgCfEFcg/f///6U3598FshhLgvyCGRye3UgDcuw9XRxDKub0nrIWZFAQcD54R4GBM8JVKmiC40EBu+mvK8+KcXrozanILvK6Zv3UfI7PohLz1sNbC3ZN2PaF+6f6J7aIIvW5WW7/1YBGMXi6+rmsc0poAgAsQzC9"
            }
        }
    ],
    "size": {
        "height": 1000,
        "width": 1000
    }
}